DrukBam/MapPlot.py
DrukBam/PlotCalc.py
DrukBam/__init__.py
DrukBam/__main__.py
DrukBam/bamCalc.py
DrukBam/classic.ini
DrukBam/setup.py
DrukBam/vcfParse.py
drukbam-1.1.4.dist-info/METADATA
drukbam-1.1.4.dist-info/WHEEL
drukbam-1.1.4.dist-info/entry_points.txt
drukbam-1.1.4.dist-info/RECORD
